{
  "version": "2.0",
  "extensions": {
    "mcp": {
      "instructions": "Servidor MCP para ...",
      "serverName": "name_mcp",
      "serverVersion": "2.0.0",
      "messageOptions": {
        "useAbsoluteUriForEndpoint": false
      }
    }    
  },
  "logging": {
    "applicationInsights": {
      "samplingSettings": {
        "isEnabled": true,
        "excludedTypes": "Request"
      }
    }
  },
  "extensionBundle": {
    "id": "Microsoft.Azure.Functions.ExtensionBundle.Preview",
    "version": "[4.0.0, 5.0.0)"
  }
}